README.rst
requirements.txt
setup.py
migrator/__init__.py
migrator/cli.py
migrator/code_generator.py
migrator/collector.py
migrator/config.py
migrator/db_inspector.py
migrator/executor.py
migrator/fixtures.py
migrator/utils.py
peewee_migrator.egg-info/PKG-INFO
peewee_migrator.egg-info/SOURCES.txt
peewee_migrator.egg-info/dependency_links.txt
peewee_migrator.egg-info/entry_points.txt
peewee_migrator.egg-info/requires.txt
peewee_migrator.egg-info/top_level.txt